MANIFEST.in
setup.py
RESOURCES/.suffix
RESOURCES/dummy
ematmap/__init__.py
ematmap/bin.py
ematmap/bool.py
ematmap/dulr.py
ematmap/durl.py
ematmap/ematmap.py
ematmap/engine.py
ematmap/filter_dulr.py
ematmap/filter_durl.py
ematmap/filter_engine.py
ematmap/filter_udlr.py
ematmap/filter_udrl.py
ematmap/groupby_dulr.py
ematmap/groupby_durl.py
ematmap/groupby_engine.py
ematmap/groupby_udlr.py
ematmap/groupby_udrl.py
ematmap/udlr.py
ematmap/udrl.py
ematmap/utils.py
ematmap.egg-info/PKG-INFO
ematmap.egg-info/SOURCES.txt
ematmap.egg-info/dependency_links.txt
ematmap.egg-info/entry_points.txt
ematmap.egg-info/top_level.txt