Metadata-Version: 1.1
Name: ematmap
Version: 0.6
Summary: mat map
Home-page: https://github.com/ihgazni2/ematmap
Author: ihgazni2
Author-email: UNKNOWN
License: MIT
Platform: UNKNOWN
Classifier: Environment :: Console
Classifier: Environment :: Web Environment
Classifier: Intended Audience :: End Users/Desktop
Classifier: Intended Audience :: Developers
Classifier: Intended Audience :: System Administrators
Classifier: Programming Language :: Python
